{
    "@context": [
        "sdf.s3.jsonld",
        {
            "cmu": "https://www.cmu.edu/"
        }
    ],
    "sdfVersion": "2.2",
    "@id": "paper57R",
    "version": "v0",
    "events": [
        {
            "@id": "ev1",
            "name": "Environmental performance of EV batteries",
            "participants": [],
            "children": [
                {
                    "child": "ev1.1",
                    "importance": 1
                },
                {
                    "child": "ev1.2",
                    "importance": 1
                },
                {
                    "child": "ev1.3",
                    "importance": 1
                },
                {
                    "child": "ev1.4",
                    "importance": 1
                },
                {
                    "child": "ev1.5",
                    "importance": 1
                },
                {
                    "child": "ev1.6",
                    "importance": 1
                },
                {
                    "child": "paper57/Event/7kotseu73/Transition-to-higher-nickel-lower-cobalt-NMC-batteries",
                    "importance": 1
                },
                {
                    "child": "paper57/Event/30aHpONT10/GREET-life-cycle-assessment-model",
                    "importance": 1
                },
                {
                    "child": "paper57/Event/1S6X9cFr2F/GHG-and-SOx-emissions-variability",
                    "importance": 1
                },
                {
                    "child": "paper57/Event/2irDPH0KNe/Impact-of-production-location",
                    "importance": 1
                }
            ],
            "children_gate": "and",
            "wd_node": "",
            "wd_label": "Environmental performance of EV batteries",
            "wd_description": "The environmental performance of EV batteries is significantly influenced by their chemistry and production location. Transitioning to higher-nickel, lower-cobalt, high-performance automotive lithium nickel manganese cobalt oxide (NMC) lithium-ion batteries (LIBs) from the base NMC111 can reduce GHG emissions but increase SOx emissions.",
            "description": "The environmental performance of EV batteries is significantly influenced by their chemistry and production location. Transitioning to higher-nickel, lower-cobalt, high-performance automotive lithium nickel manganese cobalt oxide (NMC) lithium-ion batteries (LIBs) from the base NMC111 can reduce GHG emissions but increase SOx emissions."
        },
        {
            "@id": "ev1.1",
            "name": "Higher-nickel NMC cathodes",
            "participants": [],
            "wd_node": "",
            "wd_label": "Higher-nickel NMC cathodes",
            "wd_description": "Transitioning to higher-nickel NMC cathodes can potentially increase the energy density of EV batteries.",
            "description": "Transitioning to higher-nickel NMC cathodes can potentially increase the energy density of EV batteries."
        },
        {
            "@id": "ev1.2",
            "name": "Lower-cobalt NMC cathodes",
            "participants": [],
            "wd_node": "",
            "wd_label": "Lower-cobalt NMC cathodes",
            "wd_description": "Transitioning to lower-cobalt NMC cathodes is favored in the industry.",
            "description": "Transitioning to lower-cobalt NMC cathodes is favored in the industry."
        },
        {
            "@id": "ev1.3",
            "name": "GHG emissions",
            "participants": [],
            "wd_node": "",
            "wd_label": "GHG emissions",
            "wd_description": "Transitioning to NMC532, NMC622, and NMC811 cathodes can reduce GHG emissions relative to NMC111.",
            "description": "Transitioning to NMC532, NMC622, and NMC811 cathodes can reduce GHG emissions relative to NMC111."
        },
        {
            "@id": "ev1.4",
            "name": "SOx emissions",
            "participants": [],
            "wd_node": "",
            "wd_label": "SOx emissions",
            "wd_description": "Transitioning to NMC532, NMC622, and NMC811 cathodes can increase SOx emissions significantly relative to NMC111.",
            "description": "Transitioning to NMC532, NMC622, and NMC811 cathodes can increase SOx emissions significantly relative to NMC111."
        },
        {
            "@id": "ev1.5",
            "name": "Energy density",
            "participants": [],
            "wd_node": "",
            "wd_label": "Energy density",
            "wd_description": "Higher-nickel NMC cathodes increase the energy density of EV batteries.",
            "description": "Higher-nickel NMC cathodes increase the energy density of EV batteries."
        },
        {
            "@id": "ev1.6",
            "name": "Production location",
            "participants": [],
            "wd_node": "",
            "wd_label": "Production location",
            "wd_description": "The environmental performance of EV batteries is influenced by the production location, considering factors like the electricity grid and mineral extraction methods.",
            "description": "The environmental performance of EV batteries is influenced by the production location, considering factors like the electricity grid and mineral extraction methods."
        },
        {
            "@id": "ev2",
            "name": "Projected increase in EV sales and battery manufacturing capacity",
            "participants": [],
            "children": [
                {
                    "child": "ev2.1",
                    "importance": 1
                },
                {
                    "child": "ev2.2",
                    "importance": 1
                },
                {
                    "child": "ev2.3",
                    "importance": 1
                },
                {
                    "child": "ev2.4",
                    "importance": 1
                },
                {
                    "child": "paper57/Event/D4SLZGvZs/Global-battery-manufacturing-capacity-projections",
                    "importance": 1
                }
            ],
            "children_gate": "and",
            "wd_node": "",
            "wd_label": "Projected increase in EV sales and battery manufacturing capacity",
            "wd_description": "The projected increase in EV sales will significantly increase battery manufacturing capacity. Global LIB manufacturing capacity is expected to grow from 40 GWh in 2014 to 2.2 TWh by 2029, with China dominating this capacity.",
            "description": "The projected increase in EV sales will significantly increase battery manufacturing capacity. Global LIB manufacturing capacity is expected to grow from 40 GWh in 2014 to 2.2 TWh by 2029, with China dominating this capacity."
        },
        {
            "@id": "ev2.1",
            "name": "EV sales increase",
            "participants": [],
            "wd_node": "",
            "wd_label": "EV sales increase",
            "wd_description": "The increase in EV sales will drive the demand for lithium-ion batteries.",
            "description": "The increase in EV sales will drive the demand for lithium-ion batteries."
        },
        {
            "@id": "ev2.2",
            "name": "Battery manufacturing capacity",
            "participants": [],
            "wd_node": "",
            "wd_label": "Battery manufacturing capacity",
            "wd_description": "Global LIB manufacturing capacity is projected to increase significantly, reaching 2.2 TWh by 2029.",
            "description": "Global LIB manufacturing capacity is projected to increase significantly, reaching 2.2 TWh by 2029."
        },
        {
            "@id": "ev2.3",
            "name": "China",
            "participants": [],
            "wd_node": "",
            "wd_label": "China",
            "wd_description": "China currently dominates battery manufacturing capacity and is expected to continue dominating it through 2029.",
            "description": "China currently dominates battery manufacturing capacity and is expected to continue dominating it through 2029."
        },
        {
            "@id": "ev2.4",
            "name": "Europe",
            "participants": [],
            "wd_node": "",
            "wd_label": "Europe",
            "wd_description": "Countries in Europe are investing in battery manufacturing, with a total projected capacity of 240 GWh by the end of the decade.",
            "description": "Countries in Europe are investing in battery manufacturing, with a total projected capacity of 240 GWh by the end of the decade."
        },
        {
            "@id": "ev3",
            "name": "Life-cycle assessment (LCA) of LIB production",
            "participants": [],
            "children": [
                {
                    "child": "ev3.1",
                    "importance": 1
                },
                {
                    "child": "ev3.2",
                    "importance": 1
                },
                {
                    "child": "ev3.3",
                    "importance": 1
                },
                {
                    "child": "ev3.4",
                    "importance": 1
                },
                {
                    "child": "ev3.5",
                    "importance": 1
                }
            ],
            "children_gate": "and",
            "wd_node": "",
            "wd_label": "Life-cycle assessment (LCA) of LIB production",
            "wd_description": "LCA is used to examine the environmental impacts of LIB production, including the variability in electricity grid profiles and the transition to high-nickel NMC batteries.",
            "description": "LCA is used to examine the environmental impacts of LIB production, including the variability in electricity grid profiles and the transition to high-nickel NMC batteries."
        },
        {
            "@id": "ev3.1",
            "name": "LCA",
            "participants": [],
            "wd_node": "",
            "wd_label": "LCA",
            "wd_description": "LCA is used to assess the environmental impacts of LIB production across different stages of the product life cycle.",
            "description": "LCA is used to assess the environmental impacts of LIB production across different stages of the product life cycle."
        },
        {
            "@id": "ev3.2",
            "name": "Electricity grid variability",
            "participants": [],
            "wd_node": "",
            "wd_label": "Electricity grid variability",
            "wd_description": "Variability in the electricity grid profiles affects the environmental impacts of LIB production.",
            "description": "Variability in the electricity grid profiles affects the environmental impacts of LIB production."
        },
        {
            "@id": "ev3.3",
            "name": "High-nickel NMC batteries",
            "participants": [],
            "wd_node": "",
            "wd_label": "High-nickel NMC batteries",
            "wd_description": "Transitioning to high-nickel NMC batteries is examined to understand its impact on the life-cycle environmental impacts of LIB production.",
            "description": "Transitioning to high-nickel NMC batteries is examined to understand its impact on the life-cycle environmental impacts of LIB production."
        },
        {
            "@id": "ev3.4",
            "name": "Cobalt supply risk",
            "participants": [],
            "wd_node": "",
            "wd_label": "Cobalt supply risk",
            "wd_description": "Cobalt is considered the highest material supply chain risk for EVs in the short and medium term.",
            "description": "Cobalt is considered the highest material supply chain risk for EVs in the short and medium term."
        },
        {
            "@id": "ev3.5",
            "name": "Nickel demand",
            "participants": [],
            "wd_node": "",
            "wd_label": "Nickel demand",
            "wd_description": "The shift toward higher nickel content in LIBs increases the demand for nickel, impacting the supply chain.",
            "description": "The shift toward higher nickel content in LIBs increases the demand for nickel, impacting the supply chain."
        },
        {
            "@id": "ev4",
            "name": "Impact of regional variability on LIB production",
            "participants": [],
            "children": [
                {
                    "child": "ev4.1",
                    "importance": 1
                },
                {
                    "child": "ev4.2",
                    "importance": 1
                },
                {
                    "child": "ev4.3",
                    "importance": 1
                }
            ],
            "children_gate": "and",
            "wd_node": "",
            "wd_label": "Impact of regional variability on LIB production",
            "wd_description": "The regional variability in electricity profiles and nickel feedstock significantly influences the environmental impacts of LIB production.",
            "description": "The regional variability in electricity profiles and nickel feedstock significantly influences the environmental impacts of LIB production."
        },
        {
            "@id": "ev4.1",
            "name": "Electricity profiles",
            "participants": [],
            "wd_node": "",
            "wd_label": "Electricity profiles",
            "wd_description": "The regional variability in electricity profiles affects the GHG emissions and water consumption levels of LIB production.",
            "description": "The regional variability in electricity profiles affects the GHG emissions and water consumption levels of LIB production."
        },
        {
            "@id": "ev4.2",
            "name": "Nickel feedstock",
            "participants": [],
            "wd_node": "",
            "wd_label": "Nickel feedstock",
            "wd_description": "The choice of nickel feedstock affects the environmental impacts of LIB production, particularly GHG and SOx emissions.",
            "description": "The choice of nickel feedstock affects the environmental impacts of LIB production, particularly GHG and SOx emissions."
        },
        {
            "@id": "ev4.3",
            "name": "Regional variability",
            "participants": [],
            "wd_node": "",
            "wd_label": "Regional variability",
            "wd_description": "The regional variability of the supply chain influences the environmental performance of LIB production.",
            "description": "The regional variability of the supply chain influences the environmental performance of LIB production."
        },
        {
            "@id": "ev5",
            "name": "Role of cobalt in LIB production",
            "participants": [],
            "children": [
                {
                    "child": "ev5.1",
                    "importance": 1
                },
                {
                    "child": "ev5.2",
                    "importance": 1
                },
                {
                    "child": "ev5.3",
                    "importance": 1
                },
                {
                    "child": "ev5.4",
                    "importance": 1
                }
            ],
            "children_gate": "and",
            "wd_node": "",
            "wd_label": "Role of cobalt in LIB production",
            "wd_description": "Cobalt is primarily recovered as a byproduct from copper and nickel mines, with significant production in the Democratic Republic of Congo and China. The refining stage of cobalt sulfate production is the most energy-intensive.",
            "description": "Cobalt is primarily recovered as a byproduct from copper and nickel mines, with significant production in the Democratic Republic of Congo and China. The refining stage of cobalt sulfate production is the most energy-intensive."
        },
        {
            "@id": "ev5.1",
            "name": "Cobalt",
            "participants": [],
            "wd_node": "",
            "wd_label": "Cobalt",
            "wd_description": "Cobalt is recovered as a byproduct from copper and nickel mines.",
            "description": "Cobalt is recovered as a byproduct from copper and nickel mines."
        },
        {
            "@id": "ev5.2",
            "name": "Democratic Republic of Congo",
            "participants": [],
            "wd_node": "",
            "wd_label": "Democratic Republic of Congo",
            "wd_description": "The Democratic Republic of Congo is the leading source of mined cobalt.",
            "description": "The Democratic Republic of Congo is the leading source of mined cobalt."
        },
        {
            "@id": "ev5.3",
            "name": "China",
            "participants": [],
            "wd_node": "",
            "wd_label": "China",
            "wd_description": "China is a significant producer of cobalt sulfate and cobalt oxide.",
            "description": "China is a significant producer of cobalt sulfate and cobalt oxide."
        },
        {
            "@id": "ev5.4",
            "name": "Refining stage",
            "participants": [],
            "wd_node": "",
            "wd_label": "Refining stage",
            "wd_description": "The refining stage of cobalt sulfate production is the most energy-intensive.",
            "description": "The refining stage of cobalt sulfate production is the most energy-intensive."
        },
        {
            "@id": "ev6",
            "name": "Importance of aluminum in LIB components",
            "participants": [],
            "children": [
                {
                    "child": "ev6.1",
                    "importance": 1
                },
                {
                    "child": "ev6.2",
                    "importance": 1
                },
                {
                    "child": "ev6.3",
                    "importance": 1
                },
                {
                    "child": "ev6.4",
                    "importance": 1
                },
                {
                    "child": "paper57/Event/2hpHOm6OAN/Energy-intensive-aluminum-production",
                    "importance": 1
                },
                {
                    "child": "paper57/Event/2Jle0GhSV0/Regional-variability-in-aluminum-production",
                    "importance": 1
                }
            ],
            "children_gate": "and",
            "wd_node": "",
            "wd_label": "Importance of aluminum in LIB components",
            "wd_description": "Several components of LIBs are made of aluminum, which involves energy-intensive production processes. The study examines the environmental impacts of aluminum produced from different regions and energy sources.",
            "description": "Several components of LIBs are made of aluminum, which involves energy-intensive production processes. The study examines the environmental impacts of aluminum produced from different regions and energy sources."
        },
        {
            "@id": "ev6.1",
            "name": "Aluminum components",
            "participants": [],
            "wd_node": "",
            "wd_label": "Aluminum components",
            "wd_description": "Aluminum is used in several components of LIBs, including the positive foil and positive terminal assembly.",
            "description": "Aluminum is used in several components of LIBs, including the positive foil and positive terminal assembly."
        },
        {
            "@id": "ev6.2",
            "name": "Energy-intensive production",
            "participants": [],
            "wd_node": "",
            "wd_label": "Energy-intensive production",
            "wd_description": "Primary aluminum production is energy-intensive, involving the Bayer process and the Hall-Heroult smelting process.",
            "description": "Primary aluminum production is energy-intensive, involving the Bayer process and the Hall-Heroult smelting process."
        },
        {
            "@id": "ev6.3",
            "name": "Regional variability",
            "participants": [],
            "wd_node": "",
            "wd_label": "Regional variability",
            "wd_description": "The environmental impacts of aluminum production vary based on the region and energy mix used.",
            "description": "The environmental impacts of aluminum production vary based on the region and energy mix used."
        },
        {
            "@id": "ev6.4",
            "name": "Energy sources",
            "participants": [],
            "wd_node": "",
            "wd_label": "Energy sources",
            "wd_description": "The study examines aluminum produced from hydro- and wind-powered electricity sources.",
            "description": "The study examines aluminum produced from hydro- and wind-powered electricity sources."
        },
        {
            "@id": "ev7",
            "name": "Role of Battery Management System (BMS) in LIBs",
            "participants": [],
            "children": [
                {
                    "child": "ev7.1",
                    "importance": 1
                },
                {
                    "child": "ev7.2",
                    "importance": 1
                },
                {
                    "child": "ev7.3",
                    "importance": 1
                },
                {
                    "child": "ev7.4",
                    "importance": 1
                },
                {
                    "child": "paper57/Event/3XeJorx2Ne/BMS-production-variability",
                    "importance": 1
                }
            ],
            "children_gate": "and",
            "wd_node": "",
            "wd_label": "Role of Battery Management System (BMS) in LIBs",
            "wd_description": "The BMS controls the interactions between the LIB and the required load to ensure safe and reliable operation. The study models BMS production in different regions.",
            "description": "The BMS controls the interactions between the LIB and the required load to ensure safe and reliable operation. The study models BMS production in different regions."
        },
        {
            "@id": "ev7.1",
            "name": "BMS",
            "participants": [],
            "wd_node": "",
            "wd_label": "BMS",
            "wd_description": "The BMS controls interactions between the LIB and the required load.",
            "description": "The BMS controls interactions between the LIB and the required load."
        },
        {
            "@id": "ev7.2",
            "name": "Safe operation",
            "participants": [],
            "wd_node": "",
            "wd_label": "Safe operation",
            "wd_description": "The BMS ensures the safe operation of the LIB by preventing overcharging and complete discharge.",
            "description": "The BMS ensures the safe operation of the LIB by preventing overcharging and complete discharge."
        },
        {
            "@id": "ev7.3",
            "name": "Reliable operation",
            "participants": [],
            "wd_node": "",
            "wd_label": "Reliable operation",
            "wd_description": "The BMS ensures the reliable operation of the LIB by monitoring battery operations.",
            "description": "The BMS ensures the reliable operation of the LIB by monitoring battery operations."
        },
        {
            "@id": "ev7.4",
            "name": "Regional variability",
            "participants": [],
            "wd_node": "",
            "wd_label": "Regional variability",
            "wd_description": "The study models BMS production in different regions, similar to cell production scenarios.",
            "description": "The study models BMS production in different regions, similar to cell production scenarios."
        },
        {
            "@id": "paper57/Event/7kotseu73/Transition-to-higher-nickel-lower-cobalt-NMC-batteries",
            "name": "Transition to higher nickel lower cobalt NMC batteries",
            "ta1explanation": "",
            "description": "Transitioning to higher-nickel and lower-cobalt NMC batteries influences the environmental impacts of LIB production, increasing energy density but also SOx emissions.",
            "wd_node": "paper57",
            "wd_label": "paper57",
            "participants": []
        },
        {
            "@id": "paper57/Event/30aHpONT10/GREET-life-cycle-assessment-model",
            "name": "GREET life cycle assessment model",
            "ta1explanation": "",
            "description": "The GREET model is used to conduct environmental analysis focusing on differences among global regions in production conditions.",
            "wd_node": "paper57",
            "wd_label": "paper57",
            "participants": []
        },
        {
            "@id": "paper57/Event/1S6X9cFr2F/GHG-and-SOx-emissions-variability",
            "name": "GHG and SOx emissions variability",
            "ta1explanation": "",
            "description": "GHG and SOx emissions levels vary significantly with the type of nickel precursor and production pathway",
            "wd_node": "paper57",
            "wd_label": "paper57",
            "participants": []
        },
        {
            "@id": "paper57/Event/2irDPH0KNe/Impact-of-production-location",
            "name": "Impact of production location",
            "ta1explanation": "",
            "description": "Production location impacts environmental performance, with hydro-powered electricity reducing GHG emissions but increasing water consumption.",
            "wd_node": "paper57",
            "wd_label": "paper57",
            "participants": []
        },
        {
            "@id": "paper57/Event/D4SLZGvZs/Global-battery-manufacturing-capacity-projections",
            "name": "Global battery manufacturing capacity projections",
            "ta1explanation": "",
            "description": "Battery manufacturing capacity is projected to increase significantly, with China dominating but other regions like Europe also investing heavily.",
            "wd_node": "paper57",
            "wd_label": "paper57",
            "participants": []
        },
        {
            "@id": "paper57/Event/2hpHOm6OAN/Energy-intensive-aluminum-production",
            "name": "Energy intensive aluminum production",
            "ta1explanation": "",
            "description": "Aluminum production is energy-intensive, particularly the smelting process, which significantly impacts the overall environmental footprint.",
            "wd_node": "paper57",
            "wd_label": "paper57",
            "participants": []
        },
        {
            "@id": "paper57/Event/2Jle0GhSV0/Regional-variability-in-aluminum-production",
            "name": "Regional variability in aluminum production",
            "ta1explanation": "",
            "description": "Aluminum production's environmental impact varies with regional electricity mixes, influencing the overall footprint of NMC LIB production.",
            "wd_node": "paper57",
            "wd_label": "paper57",
            "participants": []
        },
        {
            "@id": "paper57/Event/3XeJorx2Ne/BMS-production-variability",
            "name": "BMS production variability",
            "ta1explanation": "",
            "description": "The production of BMS varies regionally, with different energy sources affecting the overall environmental impact.",
            "wd_node": "paper57",
            "wd_label": "paper57",
            "participants": []
        }
    ],
    "relations": [
        {
            "@id": "Relations/00443/before",
            "wd_node": "wd:Q79030196",
            "wd_label": "before",
            "wd_description": "qualifies something (inception or end of a thing, event, or date) as happening previously to another thing",
            "relationSubject": "ev1.5",
            "relationObject": "ev1.6"
        },
        {
            "@id": "Relations/00443/before",
            "wd_node": "wd:Q79030196",
            "wd_label": "before",
            "wd_description": "qualifies something (inception or end of a thing, event, or date) as happening previously to another thing",
            "relationSubject": "ev1.5",
            "relationObject": "ev1.6"
        },
        {
            "@id": "Relations/00443/before",
            "wd_node": "wd:Q79030196",
            "wd_label": "before",
            "wd_description": "qualifies something (inception or end of a thing, event, or date) as happening previously to another thing",
            "relationSubject": "ev1.5",
            "relationObject": "ev1.6"
        },
        {
            "@id": "Relations/00443/before",
            "wd_node": "wd:Q79030196",
            "wd_label": "before",
            "wd_description": "qualifies something (inception or end of a thing, event, or date) as happening previously to another thing",
            "relationSubject": "ev1.5",
            "relationObject": "ev1.6"
        },
        {
            "@id": "Relations/00443/before",
            "wd_node": "wd:Q79030196",
            "wd_label": "before",
            "wd_description": "qualifies something (inception or end of a thing, event, or date) as happening previously to another thing",
            "relationSubject": "ev1.5",
            "relationObject": "ev1.6"
        },
        {
            "@id": "Relations/00443/before",
            "wd_node": "wd:Q79030196",
            "wd_label": "before",
            "wd_description": "qualifies something (inception or end of a thing, event, or date) as happening previously to another thing",
            "relationSubject": "ev1.5",
            "relationObject": "ev1.6"
        },
        {
            "@id": "Relations/00443/before",
            "wd_node": "wd:Q79030196",
            "wd_label": "before",
            "wd_description": "qualifies something (inception or end of a thing, event, or date) as happening previously to another thing",
            "relationSubject": "ev1.5",
            "relationObject": "ev1.6"
        },
        {
            "@id": "Relations/00443/before",
            "wd_node": "wd:Q79030196",
            "wd_label": "before",
            "wd_description": "qualifies something (inception or end of a thing, event, or date) as happening previously to another thing",
            "relationSubject": "ev2.3",
            "relationObject": "ev2.4"
        },
        {
            "@id": "Relations/00443/before",
            "wd_node": "wd:Q79030196",
            "wd_label": "before",
            "wd_description": "qualifies something (inception or end of a thing, event, or date) as happening previously to another thing",
            "relationSubject": "ev2.3",
            "relationObject": "ev2.4"
        },
        {
            "@id": "Relations/00443/before",
            "wd_node": "wd:Q79030196",
            "wd_label": "before",
            "wd_description": "qualifies something (inception or end of a thing, event, or date) as happening previously to another thing",
            "relationSubject": "ev2.3",
            "relationObject": "ev2.4"
        },
        {
            "@id": "Relations/00443/before",
            "wd_node": "wd:Q79030196",
            "wd_label": "before",
            "wd_description": "qualifies something (inception or end of a thing, event, or date) as happening previously to another thing",
            "relationSubject": "ev2.3",
            "relationObject": "ev2.4"
        },
        {
            "@id": "Relations/00443/before",
            "wd_node": "wd:Q79030196",
            "wd_label": "before",
            "wd_description": "qualifies something (inception or end of a thing, event, or date) as happening previously to another thing",
            "relationSubject": "ev2.3",
            "relationObject": "ev2.4"
        },
        {
            "@id": "Relations/00443/before",
            "wd_node": "wd:Q79030196",
            "wd_label": "before",
            "wd_description": "qualifies something (inception or end of a thing, event, or date) as happening previously to another thing",
            "relationSubject": "ev3.4",
            "relationObject": "ev3.5"
        },
        {
            "@id": "Relations/00443/before",
            "wd_node": "wd:Q79030196",
            "wd_label": "before",
            "wd_description": "qualifies something (inception or end of a thing, event, or date) as happening previously to another thing",
            "relationSubject": "ev3.4",
            "relationObject": "ev3.5"
        },
        {
            "@id": "Relations/00443/before",
            "wd_node": "wd:Q79030196",
            "wd_label": "before",
            "wd_description": "qualifies something (inception or end of a thing, event, or date) as happening previously to another thing",
            "relationSubject": "ev3.4",
            "relationObject": "ev3.5"
        },
        {
            "@id": "Relations/00443/before",
            "wd_node": "wd:Q79030196",
            "wd_label": "before",
            "wd_description": "qualifies something (inception or end of a thing, event, or date) as happening previously to another thing",
            "relationSubject": "ev3.4",
            "relationObject": "ev3.5"
        },
        {
            "@id": "Relations/00443/before",
            "wd_node": "wd:Q79030196",
            "wd_label": "before",
            "wd_description": "qualifies something (inception or end of a thing, event, or date) as happening previously to another thing",
            "relationSubject": "ev3.4",
            "relationObject": "ev3.5"
        },
        {
            "@id": "Relations/00443/before",
            "wd_node": "wd:Q79030196",
            "wd_label": "before",
            "wd_description": "qualifies something (inception or end of a thing, event, or date) as happening previously to another thing",
            "relationSubject": "ev3.4",
            "relationObject": "ev3.5"
        },
        {
            "@id": "Relations/00443/before",
            "wd_node": "wd:Q79030196",
            "wd_label": "before",
            "wd_description": "qualifies something (inception or end of a thing, event, or date) as happening previously to another thing",
            "relationSubject": "ev4.2",
            "relationObject": "ev4.3"
        },
        {
            "@id": "Relations/00443/before",
            "wd_node": "wd:Q79030196",
            "wd_label": "before",
            "wd_description": "qualifies something (inception or end of a thing, event, or date) as happening previously to another thing",
            "relationSubject": "ev4.2",
            "relationObject": "ev4.3"
        },
        {
            "@id": "Relations/00443/before",
            "wd_node": "wd:Q79030196",
            "wd_label": "before",
            "wd_description": "qualifies something (inception or end of a thing, event, or date) as happening previously to another thing",
            "relationSubject": "ev4.2",
            "relationObject": "ev4.3"
        },
        {
            "@id": "Relations/00443/before",
            "wd_node": "wd:Q79030196",
            "wd_label": "before",
            "wd_description": "qualifies something (inception or end of a thing, event, or date) as happening previously to another thing",
            "relationSubject": "ev4.2",
            "relationObject": "ev4.3"
        },
        {
            "@id": "Relations/00443/before",
            "wd_node": "wd:Q79030196",
            "wd_label": "before",
            "wd_description": "qualifies something (inception or end of a thing, event, or date) as happening previously to another thing",
            "relationSubject": "ev5.3",
            "relationObject": "ev5.4"
        },
        {
            "@id": "Relations/00443/before",
            "wd_node": "wd:Q79030196",
            "wd_label": "before",
            "wd_description": "qualifies something (inception or end of a thing, event, or date) as happening previously to another thing",
            "relationSubject": "ev5.3",
            "relationObject": "ev5.4"
        },
        {
            "@id": "Relations/00443/before",
            "wd_node": "wd:Q79030196",
            "wd_label": "before",
            "wd_description": "qualifies something (inception or end of a thing, event, or date) as happening previously to another thing",
            "relationSubject": "ev5.3",
            "relationObject": "ev5.4"
        },
        {
            "@id": "Relations/00443/before",
            "wd_node": "wd:Q79030196",
            "wd_label": "before",
            "wd_description": "qualifies something (inception or end of a thing, event, or date) as happening previously to another thing",
            "relationSubject": "ev5.3",
            "relationObject": "ev5.4"
        },
        {
            "@id": "Relations/00443/before",
            "wd_node": "wd:Q79030196",
            "wd_label": "before",
            "wd_description": "qualifies something (inception or end of a thing, event, or date) as happening previously to another thing",
            "relationSubject": "ev5.3",
            "relationObject": "ev5.4"
        },
        {
            "@id": "Relations/00443/before",
            "wd_node": "wd:Q79030196",
            "wd_label": "before",
            "wd_description": "qualifies something (inception or end of a thing, event, or date) as happening previously to another thing",
            "relationSubject": "ev6.3",
            "relationObject": "ev6.4"
        },
        {
            "@id": "Relations/00443/before",
            "wd_node": "wd:Q79030196",
            "wd_label": "before",
            "wd_description": "qualifies something (inception or end of a thing, event, or date) as happening previously to another thing",
            "relationSubject": "ev6.3",
            "relationObject": "ev6.4"
        },
        {
            "@id": "Relations/00443/before",
            "wd_node": "wd:Q79030196",
            "wd_label": "before",
            "wd_description": "qualifies something (inception or end of a thing, event, or date) as happening previously to another thing",
            "relationSubject": "ev6.3",
            "relationObject": "ev6.4"
        },
        {
            "@id": "Relations/00443/before",
            "wd_node": "wd:Q79030196",
            "wd_label": "before",
            "wd_description": "qualifies something (inception or end of a thing, event, or date) as happening previously to another thing",
            "relationSubject": "ev6.3",
            "relationObject": "ev6.4"
        },
        {
            "@id": "Relations/00443/before",
            "wd_node": "wd:Q79030196",
            "wd_label": "before",
            "wd_description": "qualifies something (inception or end of a thing, event, or date) as happening previously to another thing",
            "relationSubject": "ev6.3",
            "relationObject": "ev6.4"
        },
        {
            "@id": "Relations/00443/before",
            "wd_node": "wd:Q79030196",
            "wd_label": "before",
            "wd_description": "qualifies something (inception or end of a thing, event, or date) as happening previously to another thing",
            "relationSubject": "ev7.3",
            "relationObject": "ev7.4"
        },
        {
            "@id": "Relations/00443/before",
            "wd_node": "wd:Q79030196",
            "wd_label": "before",
            "wd_description": "qualifies something (inception or end of a thing, event, or date) as happening previously to another thing",
            "relationSubject": "ev7.3",
            "relationObject": "ev7.4"
        },
        {
            "@id": "Relations/00443/before",
            "wd_node": "wd:Q79030196",
            "wd_label": "before",
            "wd_description": "qualifies something (inception or end of a thing, event, or date) as happening previously to another thing",
            "relationSubject": "ev7.3",
            "relationObject": "ev7.4"
        },
        {
            "@id": "Relations/00443/before",
            "wd_node": "wd:Q79030196",
            "wd_label": "before",
            "wd_description": "qualifies something (inception or end of a thing, event, or date) as happening previously to another thing",
            "relationSubject": "ev7.3",
            "relationObject": "ev7.4"
        },
        {
            "@id": "Relations/00443/before",
            "wd_node": "wd:Q79030196",
            "wd_label": "before",
            "wd_description": "qualifies something (inception or end of a thing, event, or date) as happening previously to another thing",
            "relationSubject": "ev7.3",
            "relationObject": "ev7.4"
        }
    ],
    "entities": []
}